{
    "s":1,
    "m":"ok",
    "d":[
        {
            "tag":"前端",
            "users":[
                {
                    "objectId":"5928e14644d90400641dec8a",
                    "selfDescription":"人人网前端团队",
                    "company":"人人网",
                    "jobTitle":"",
                    "avatarLarge":"https://user-gold-cdn.xitu.io/2017/5/30/54d9e4807358cf498a123d0046941b23",
                    "username":"人人网FED"
                },
                {
                    "objectId":"5abdf16f6fb9a028d1413539",
                    "selfDescription":"在美团，我们信仰耐心和坚持的力量，愿意持续去做一些正确、有积累、可能表面看上去不那么重要实则非常关键的事情。",
                    "company":"美团",
                    "jobTitle":"美团小编",
                    "avatarLarge":"https://user-gold-cdn.xitu.io/2018/5/28/163a63a05bdbb8f2?w=1042&h=1042&f=jpeg&s=157008",
                    "username":"美团技术团队"
                },
                {
                    "objectId":"5916b8c60ce4630069e4718c",
                    "selfDescription":"God bless us everyone",
                    "company":"你没听过的公司",
                    "jobTitle":"前端救火狮",
                    "avatarLarge":"https://user-gold-cdn.xitu.io/2018/6/27/1643ed1854a16e79?w=1546&h=1546&f=jpeg&s=462384",
                    "username":"郑昊川"
                },
                {
                    "objectId":"5b8291bce51d4538ab043911",
                    "selfDescription":"多学多练",
                    "company":"杭州麦壳麦粒有限公司",
                    "jobTitle":"软件工程师",
                    "avatarLarge":"https://user-gold-cdn.xitu.io/2018/8/26/1657609d0bf666d0?w=638&h=626&f=png&s=470795",
                    "username":"信心"
                },
                {
                    "objectId":"58a2af20128fe100582c96e9",
                    "selfDescription":"",
                    "company":"",
                    "jobTitle":"Web 前端开发",
                    "avatarLarge":"https://user-gold-cdn.xitu.io/2018/6/12/163f3162b15966d5?w=750&h=736&f=png&s=309819",
                    "username":"IridescentMia"
                },
                {
                    "objectId":"576c841f2e958a00571bf231",
                    "selfDescription":"FE,Design,Php",
                    "company":"Freleap Tech inc.",
                    "jobTitle":"Web Developer",
                    "avatarLarge":"https://user-gold-cdn.xitu.io/2018/5/17/1636c34ac26c216b?w=994&h=994&f=jpeg&s=306298",
                    "username":"蒲小花"
                },
                {
                    "objectId":"5b2061516fb9a01e53283bb4",
                    "selfDescription":"学无止境",
                    "company":"hdu",
                    "jobTitle":"全栈工程师",
                    "avatarLarge":"http://thirdwx.qlogo.cn/mmopen/vi_32/Q0j4TwGTfTL74JktfK6pP2QFBJWibpXC6ETNiaeZHxKfBMTSTLwu28m9spYmBkrtnr3DzgBc5iaTjiblwMRYAYG2ng/132",
                    "username":"～藕爸～"
                },
                {
                    "objectId":"599a9277f265da246c4a0cdb",
                    "selfDescription":"迅雷前端（XunleiF2E）是由一群年轻、富有创造力、自我驱动力的前端同学组成的团队，主要支撑迅雷客户端及 Web 类业务发展。我们鼓励分享、沉淀、输出和技术创新，让开发更高效率，让业务更好发展",
                    "company":"迅雷",
                    "jobTitle":"前端团队",
                    "avatarLarge":"https://user-gold-cdn.xitu.io/2017/8/21/b0069a088cf9fd36bb04286be464a535",
                    "username":"迅雷前端"
                }
            ]
        }
    ]
}